{
  "pli-tv-bu-vb-ss": {
    "original_title": "Saṅghādisesa",
    "translated_title": "Suspension"
  },
  "pli-tv-bu-vb-ss1": {
    "original_title": "Sukkavisaṭṭhi",
    "translated_title": "The training rule on masturbation"
  },
  "pli-tv-bu-vb-ss2": {
    "original_title": "Kāyasaṁsagga",
    "translated_title": "Physical contact with a woman"
  },
  "pli-tv-bu-vb-ss3": {
    "original_title": "Duṭṭhullavācā",
    "translated_title": "Indecent speech"
  },
  "pli-tv-bu-vb-ss4": {
    "original_title": "Attakāmpāricariya",
    "translated_title": "Encouraging a woman to satisfy one’s desires"
  },
  "pli-tv-bu-vb-ss5": {
    "original_title": "Sañcaritta",
    "translated_title": "Matchmaking"
  },
  "pli-tv-bu-vb-ss6": {
    "original_title": "Kuṭikāra",
    "translated_title": "Building a hut inappropriately"
  },
  "pli-tv-bu-vb-ss7": {
    "original_title": "Vihārakāra",
    "translated_title": "Building a dwelling inappropriately"
  },
  "pli-tv-bu-vb-ss8": {
    "original_title": "Duṭṭhadosa",
    "translated_title": "Making a groundless accusation out of anger"
  },
  "pli-tv-bu-vb-ss9": {
    "original_title": "Aññabhāgiya",
    "translated_title": "Making a groundless accusation out of anger, using a pretext"
  },
  "pli-tv-bu-vb-ss10": {
    "original_title": "Saṅghabheda",
    "translated_title": "Causing a schism in the Sangha"
  },
  "pli-tv-bu-vb-ss11": {
    "original_title": "Bhedānuvattaka",
    "translated_title": "Siding with a schismatic"
  },
  "pli-tv-bu-vb-ss12": {
    "original_title": "Dubbaca",
    "translated_title": "Being difficult to correct"
  },
  "pli-tv-bu-vb-ss13": {
    "original_title": "Kuladūsaka",
    "translated_title": "Being a corrupter of families"
  }
}