{
  "pli-tv-kd1": [
    "brahmali",
    "horner"
  ],
  "pli-tv-kd2": [
    "brahmali",
    "horner"
  ],
  "pli-tv-kd3": [
    "brahmali",
    "horner"
  ],
  "pli-tv-kd4": [
    "brahmali",
    "horner"
  ],
  "pli-tv-kd5": [
    "brahmali",
    "horner"
  ],
  "pli-tv-kd6": [
    "brahmali",
    "horner"
  ],
  "pli-tv-kd7": [
    "brahmali",
    "horner"
  ],
  "pli-tv-kd8": [
    "brahmali",
    "horner"
  ],
  "pli-tv-kd9": [
    "brahmali",
    "horner"
  ],
  "pli-tv-kd10": [
    "brahmali",
    "horner"
  ],
  "pli-tv-kd11": [
    "brahmali",
    "horner"
  ],
  "pli-tv-kd12": [
    "brahmali",
    "horner"
  ],
  "pli-tv-kd13": [
    "brahmali",
    "horner"
  ],
  "pli-tv-kd14": [
    "brahmali",
    "horner"
  ],
  "pli-tv-kd15": [
    "brahmali",
    "horner"
  ],
  "pli-tv-kd16": [
    "brahmali",
    "horner"
  ],
  "pli-tv-kd17": [
    "brahmali",
    "horner"
  ],
  "pli-tv-kd18": [
    "brahmali",
    "horner"
  ],
  "pli-tv-kd19": [
    "brahmali",
    "horner"
  ],
  "pli-tv-kd20": [
    "brahmali",
    "horner"
  ],
  "pli-tv-kd21": [
    "brahmali",
    "horner"
  ],
  "pli-tv-kd22": [
    "brahmali",
    "horner"
  ]
}